[
    {
        "id": "a66565d8-7f02-402e-8035-befd9d79e107",
        "name": "Abel",
        "gender": "m",
        "height": "183.00",
        "extras": {
            "Birthday": null,
            "Age": null,
            "gender": null,
            "Blood Type": null
        },
        "category": "Fictional",
        "subCat1": "Anime",
        "subCat2": "Unlight",
        "createdAt": "Aug 23, 12:21 PM",
        "updatedAt": "155 days"
    },
    {
        "id": "97d8d2b2-f4df-4e85-a0a0-16f22fbf7847",
        "name": "Ada",
        "gender": "f",
        "height": "165.00",
        "extras": {
            "Birthday": null,
            "Age": null,
            "gender": null,
            "Blood Type": null
        },
        "category": "Fictional",
        "subCat1": "Anime",
        "subCat2": "Unlight",
        "createdAt": "Aug 23, 12:21 PM",
        "updatedAt": "155 days"
    },
    {
        "id": "695e85b1-7046-4261-ba0d-e6daf659a02e",
        "name": "Alicetaria",
        "gender": "f",
        "height": "161.00",
        "extras": {
            "Birthday": null,
            "Age": null,
            "gender": null,
            "Blood Type": null
        },
        "category": "Fictional",
        "subCat1": "Anime",
        "subCat2": "Unlight",
        "createdAt": "Aug 23, 12:21 PM",
        "updatedAt": "155 days"
    },
    {
        "id": "d4230596-85b6-4281-9d65-765c81d4cf3f",
        "name": "Archibald",
        "gender": "m",
        "height": "185.00",
        "extras": {
            "Birthday": null,
            "Age": null,
            "gender": null,
            "Blood Type": null
        },
        "category": "Fictional",
        "subCat1": "Anime",
        "subCat2": "Unlight",
        "createdAt": "Aug 23, 12:21 PM",
        "updatedAt": "155 days"
    },
    {
        "id": "1f4846e3-07da-43c7-8353-a412393b0c93",
        "name": "Ariane",
        "gender": "f",
        "height": "161.00",
        "extras": {
            "Birthday": null,
            "Age": null,
            "gender": null,
            "Blood Type": null
        },
        "category": "Fictional",
        "subCat1": "Anime",
        "subCat2": "Unlight",
        "createdAt": "Aug 23, 12:21 PM",
        "updatedAt": "155 days"
    },
    {
        "id": "70f361f8-8c01-4231-b322-efed4f19e5cb",
        "name": "Asura",
        "gender": "m",
        "height": "178.00",
        "extras": {
            "Birthday": null,
            "Age": null,
            "gender": null,
            "Blood Type": null
        },
        "category": "Fictional",
        "subCat1": "Anime",
        "subCat2": "Unlight",
        "createdAt": "Aug 23, 12:21 PM",
        "updatedAt": "155 days"
    },
    {
        "id": "2ea4093c-670d-4af9-8b24-3b17c0096e19",
        "name": "Ayn",
        "gender": "f",
        "height": "160.00",
        "extras": {
            "Birthday": null,
            "Age": null,
            "gender": null,
            "Blood Type": null
        },
        "category": "Fictional",
        "subCat1": "Anime",
        "subCat2": "Unlight",
        "createdAt": "Aug 23, 12:21 PM",
        "updatedAt": "155 days"
    },
    {
        "id": "9798325c-15d9-409d-aba6-5499b8be3960",
        "name": "Belinda",
        "gender": "f",
        "height": "171.00",
        "extras": {
            "Birthday": null,
            "Age": null,
            "gender": null,
            "Blood Type": null
        },
        "category": "Fictional",
        "subCat1": "Anime",
        "subCat2": "Unlight",
        "createdAt": "Aug 23, 12:21 PM",
        "updatedAt": "155 days"
    },
    {
        "id": "0e6c5620-08d6-4bef-baa5-9717de567c26",
        "name": "Bernhard",
        "gender": "m",
        "height": "188.00",
        "extras": {
            "Birthday": null,
            "Age": null,
            "gender": null,
            "Blood Type": null
        },
        "category": "Fictional",
        "subCat1": "Anime",
        "subCat2": "Unlight",
        "createdAt": "Aug 23, 12:21 PM",
        "updatedAt": "155 days"
    },
    {
        "id": "cd7929fa-22b6-48bd-b767-69a6357683a1",
        "name": "Birgit",
        "gender": "f",
        "height": "167.00",
        "extras": {
            "Birthday": null,
            "Age": null,
            "gender": null,
            "Blood Type": null
        },
        "category": "Fictional",
        "subCat1": "Anime",
        "subCat2": "Unlight",
        "createdAt": "Aug 23, 12:21 PM",
        "updatedAt": "155 days"
    },
    {
        "id": "dfd57dda-bf1b-4476-84dc-2f99b6043a09",
        "name": "Blaise",
        "gender": "m",
        "height": "172.00",
        "extras": {
            "Birthday": null,
            "Age": null,
            "gender": null,
            "Blood Type": null
        },
        "category": "Fictional",
        "subCat1": "Anime",
        "subCat2": "Unlight",
        "createdAt": "Aug 23, 12:21 PM",
        "updatedAt": "155 days"
    },
    {
        "id": "63aefcd9-1690-4cc2-9a47-a2c39fbb5757",
        "name": "Blau",
        "gender": "f",
        "height": "164.00",
        "extras": {
            "Birthday": null,
            "Age": null,
            "gender": null,
            "Blood Type": null
        },
        "category": "Fictional",
        "subCat1": "Anime",
        "subCat2": "Unlight",
        "createdAt": "Aug 23, 12:21 PM",
        "updatedAt": "155 days"
    },
    {
        "id": "1365af04-082a-4e26-938e-ac1d38ac3299",
        "name": "Browning",
        "gender": "m",
        "height": "175.00",
        "extras": {
            "Birthday": null,
            "Age": null,
            "gender": null,
            "Blood Type": null
        },
        "category": "Fictional",
        "subCat1": "Anime",
        "subCat2": "Unlight",
        "createdAt": "Aug 23, 12:21 PM",
        "updatedAt": "155 days"
    },
    {
        "id": "4718cec5-7c85-4135-bcfb-bf1731ba9496",
        "name": "C.c.",
        "gender": "f",
        "height": "162.00",
        "extras": {
            "Birthday": null,
            "Age": null,
            "gender": null,
            "Blood Type": null
        },
        "category": "Fictional",
        "subCat1": "Anime",
        "subCat2": "Unlight",
        "createdAt": "Aug 23, 12:21 PM",
        "updatedAt": "155 days"
    },
    {
        "id": "536c0da0-26c0-4397-95d9-53a11027711f",
        "name": "Clovis",
        "gender": "m",
        "height": "182.00",
        "extras": {
            "Birthday": null,
            "Age": null,
            "gender": null,
            "Blood Type": null
        },
        "category": "Fictional",
        "subCat1": "Anime",
        "subCat2": "Unlight",
        "createdAt": "Aug 23, 12:21 PM",
        "updatedAt": "155 days"
    },
    {
        "id": "d374860c-5097-4d3b-8707-ea85dafece3d",
        "name": "Cobb",
        "gender": "m",
        "height": "181.00",
        "extras": {
            "Birthday": null,
            "Age": null,
            "gender": null,
            "Blood Type": null
        },
        "category": "Fictional",
        "subCat1": "Anime",
        "subCat2": "Unlight",
        "createdAt": "Aug 23, 12:21 PM",
        "updatedAt": "155 days"
    },
    {
        "id": "f28fcc30-3929-4faa-959e-e9a511668b18",
        "name": "Dino",
        "gender": "m",
        "height": "174.00",
        "extras": {
            "Birthday": null,
            "Age": null,
            "gender": null,
            "Blood Type": null
        },
        "category": "Fictional",
        "subCat1": "Anime",
        "subCat2": "Unlight",
        "createdAt": "Aug 23, 12:21 PM",
        "updatedAt": "155 days"
    },
    {
        "id": "f1fd58a3-d7e8-48b0-ad52-9f4c265d2142",
        "name": "Donita",
        "gender": "f",
        "height": "155.00",
        "extras": {
            "Birthday": null,
            "Age": null,
            "gender": null,
            "Blood Type": null
        },
        "category": "Fictional",
        "subCat1": "Anime",
        "subCat2": "Unlight",
        "createdAt": "Aug 23, 12:22 PM",
        "updatedAt": "155 days"
    },
    {
        "id": "8e66ca91-17c5-4719-b7a7-4582a98ef8f6",
        "name": "Epsilon",
        "gender": "m",
        "height": "202.00",
        "extras": {
            "Birthday": null,
            "Age": null,
            "gender": null,
            "Blood Type": null
        },
        "category": "Fictional",
        "subCat1": "Anime",
        "subCat2": "Unlight",
        "createdAt": "Aug 23, 12:21 PM",
        "updatedAt": "155 days"
    },
    {
        "id": "4d78a7cc-e864-4964-b435-03abe8cb3a3a",
        "name": "Eureka",
        "gender": "f",
        "height": "162.00",
        "extras": {
            "Birthday": null,
            "Age": null,
            "gender": null,
            "Blood Type": null
        },
        "category": "Fictional",
        "subCat1": "Anime",
        "subCat2": "Unlight",
        "createdAt": "Aug 23, 12:21 PM",
        "updatedAt": "155 days"
    },
    {
        "id": "39df5845-6a6c-43c1-a519-61c423a3b208",
        "name": "Evarist",
        "gender": "m",
        "height": "178.00",
        "extras": {
            "Birthday": null,
            "Age": null,
            "gender": null,
            "Blood Type": null
        },
        "category": "Fictional",
        "subCat1": "Anime",
        "subCat2": "Unlight",
        "createdAt": "Aug 23, 12:21 PM",
        "updatedAt": "155 days"
    },
    {
        "id": "a0e110ff-739e-40e2-a225-95db21c1edbb",
        "name": "Evelyn",
        "gender": "f",
        "height": "158.00",
        "extras": {
            "Birthday": null,
            "Age": null,
            "gender": null,
            "Blood Type": null
        },
        "category": "Fictional",
        "subCat1": "Anime",
        "subCat2": "Unlight",
        "createdAt": "Aug 23, 12:21 PM",
        "updatedAt": "155 days"
    },
    {
        "id": "ff0f90bf-553e-455a-9574-b46ec664069c",
        "name": "Florence",
        "gender": "f",
        "height": "168.00",
        "extras": {
            "Birthday": null,
            "Age": null,
            "gender": null,
            "Blood Type": null
        },
        "category": "Fictional",
        "subCat1": "Anime",
        "subCat2": "Unlight",
        "createdAt": "Aug 23, 12:21 PM",
        "updatedAt": "155 days"
    },
    {
        "id": "2543d524-42fb-4749-964a-247993e6ff2e",
        "name": "Friedrich",
        "gender": "m",
        "height": "188.00",
        "extras": {
            "Birthday": null,
            "Age": null,
            "gender": null,
            "Blood Type": null
        },
        "category": "Fictional",
        "subCat1": "Anime",
        "subCat2": "Unlight",
        "createdAt": "Aug 23, 12:21 PM",
        "updatedAt": "155 days"
    },
    {
        "id": "5697590e-3987-44bb-a550-e3f3c59fb55f",
        "name": "Gregor",
        "gender": "m",
        "height": "154.00",
        "extras": {
            "Birthday": null,
            "Age": null,
            "gender": null,
            "Blood Type": null
        },
        "category": "Fictional",
        "subCat1": "Anime",
        "subCat2": "Unlight",
        "createdAt": "Aug 23, 12:22 PM",
        "updatedAt": "155 days"
    },
    {
        "id": "204d7f40-984c-4df8-bffe-3168f3b422c8",
        "name": "Grunwald",
        "gender": "m",
        "height": "180.00",
        "extras": {
            "Birthday": null,
            "Age": null,
            "gender": null,
            "Blood Type": null
        },
        "category": "Fictional",
        "subCat1": "Anime",
        "subCat2": "Unlight",
        "createdAt": "Aug 23, 12:21 PM",
        "updatedAt": "155 days"
    },
    {
        "id": "6c3aac3f-83f6-4376-8e4a-a53d1a525cd7",
        "name": "Gustave",
        "gender": "m",
        "height": "173.00",
        "extras": {
            "Birthday": null,
            "Age": null,
            "gender": null,
            "Blood Type": null
        },
        "category": "Fictional",
        "subCat1": "Anime",
        "subCat2": "Unlight",
        "createdAt": "Aug 23, 12:21 PM",
        "updatedAt": "155 days"
    },
    {
        "id": "723148a3-88f0-41c3-b639-be6293ee6b95",
        "name": "Hugo",
        "gender": "m",
        "height": "173.00",
        "extras": {
            "Birthday": null,
            "Age": null,
            "gender": null,
            "Blood Type": null
        },
        "category": "Fictional",
        "subCat1": "Anime",
        "subCat2": "Unlight",
        "createdAt": "Aug 23, 12:21 PM",
        "updatedAt": "155 days"
    },
    {
        "id": "3c0e5559-7411-42de-abd5-267898791a94",
        "name": "Ideriha",
        "gender": "m",
        "height": "176.00",
        "extras": {
            "Birthday": null,
            "Age": null,
            "gender": null,
            "Blood Type": null
        },
        "category": "Fictional",
        "subCat1": "Anime",
        "subCat2": "Unlight",
        "createdAt": "Aug 23, 12:21 PM",
        "updatedAt": "155 days"
    },
    {
        "id": "40e84474-d739-4004-b8e0-ded20a132771",
        "name": "Izac",
        "gender": "m",
        "height": "174.00",
        "extras": {
            "Birthday": null,
            "Age": null,
            "gender": null,
            "Blood Type": null
        },
        "category": "Fictional",
        "subCat1": "Anime",
        "subCat2": "Unlight",
        "createdAt": "Aug 23, 12:21 PM",
        "updatedAt": "155 days"
    },
    {
        "id": "8d37ef0e-cf98-4e7d-b92a-91775f4b872c",
        "name": "Jamie",
        "gender": "f",
        "height": "155.00",
        "extras": {
            "Birthday": null,
            "Age": null,
            "gender": null,
            "Blood Type": null
        },
        "category": "Fictional",
        "subCat1": "Anime",
        "subCat2": "Unlight",
        "createdAt": "Aug 23, 12:22 PM",
        "updatedAt": "155 days"
    },
    {
        "id": "f174b5f4-0d74-4a46-9d4f-74a97857713c",
        "name": "Jead",
        "gender": "f",
        "height": "164.00",
        "extras": {
            "Birthday": null,
            "Age": null,
            "gender": null,
            "Blood Type": null
        },
        "category": "Fictional",
        "subCat1": "Anime",
        "subCat2": "Unlight",
        "createdAt": "Aug 23, 12:21 PM",
        "updatedAt": "155 days"
    },
    {
        "id": "b9bea9e6-1245-4cce-bf0e-cbadf23b846e",
        "name": "Judith",
        "gender": "f",
        "height": "169.00",
        "extras": {
            "Birthday": null,
            "Age": null,
            "gender": null,
            "Blood Type": null
        },
        "category": "Fictional",
        "subCat1": "Anime",
        "subCat2": "Unlight",
        "createdAt": "Aug 23, 12:21 PM",
        "updatedAt": "155 days"
    },
    {
        "id": "b2dc2009-3a7d-4bbf-8658-1f95c933f5f0",
        "name": "Juhani",
        "gender": "m",
        "height": "176.00",
        "extras": {
            "Birthday": null,
            "Age": null,
            "gender": null,
            "Blood Type": null
        },
        "category": "Fictional",
        "subCat1": "Anime",
        "subCat2": "Unlight",
        "createdAt": "Aug 23, 12:21 PM",
        "updatedAt": "155 days"
    },
    {
        "id": "cd0eb1ba-aa6f-4d04-b490-ab4d84795dbf",
        "name": "Karenberg",
        "gender": "m",
        "height": "173.00",
        "extras": {
            "Birthday": null,
            "Age": null,
            "gender": null,
            "Blood Type": null
        },
        "category": "Fictional",
        "subCat1": "Anime",
        "subCat2": "Unlight",
        "createdAt": "Aug 23, 12:21 PM",
        "updatedAt": "155 days"
    },
    {
        "id": "62f8aa6c-9cb2-4a72-a312-a351c268651e",
        "name": "Konrad",
        "gender": "m",
        "height": "171.00",
        "extras": {
            "Birthday": null,
            "Age": null,
            "gender": null,
            "Blood Type": null
        },
        "category": "Fictional",
        "subCat1": "Anime",
        "subCat2": "Unlight",
        "createdAt": "Aug 23, 12:21 PM",
        "updatedAt": "155 days"
    },
    {
        "id": "d413fa74-f065-43cb-a2ed-7eab0574ce95",
        "name": "Krnig",
        "gender": "m",
        "height": "172.00",
        "extras": {
            "Birthday": null,
            "Age": null,
            "gender": null,
            "Blood Type": null
        },
        "category": "Fictional",
        "subCat1": "Anime",
        "subCat2": "Unlight",
        "createdAt": "Aug 23, 12:22 PM",
        "updatedAt": "155 days"
    },
    {
        "id": "119b896a-b626-4e31-954d-26efe657c685",
        "name": "Kuhn",
        "gender": "m",
        "height": "184.00",
        "extras": {
            "Birthday": null,
            "Age": null,
            "gender": null,
            "Blood Type": null
        },
        "category": "Fictional",
        "subCat1": "Anime",
        "subCat2": "Unlight",
        "createdAt": "Aug 23, 12:21 PM",
        "updatedAt": "155 days"
    },
    {
        "id": "dab52d4b-b655-4b85-af52-3fe956ade17b",
        "name": "Leon",
        "gender": "m",
        "height": "178.00",
        "extras": {
            "Birthday": null,
            "Age": null,
            "gender": null,
            "Blood Type": null
        },
        "category": "Fictional",
        "subCat1": "Anime",
        "subCat2": "Unlight",
        "createdAt": "Aug 23, 12:21 PM",
        "updatedAt": "155 days"
    },
    {
        "id": "eb244f78-8979-4e5a-a843-b0c445f5ade2",
        "name": "Leta",
        "gender": "f",
        "height": "156.00",
        "extras": {
            "Birthday": null,
            "Age": null,
            "gender": null,
            "Blood Type": null
        },
        "category": "Fictional",
        "subCat1": "Anime",
        "subCat2": "Unlight",
        "createdAt": "Aug 23, 12:22 PM",
        "updatedAt": "155 days"
    },
    {
        "id": "34590e23-f0ad-45bf-aebe-ef7d1fc1e076",
        "name": "Linnaeus",
        "gender": "m",
        "height": "166.00",
        "extras": {
            "Birthday": null,
            "Age": null,
            "gender": null,
            "Blood Type": null
        },
        "category": "Fictional",
        "subCat1": "Anime",
        "subCat2": "Unlight",
        "createdAt": "Aug 23, 12:21 PM",
        "updatedAt": "155 days"
    },
    {
        "id": "e0536743-690c-4ffa-9c94-209058098d87",
        "name": "Luka",
        "gender": "m",
        "height": "179.00",
        "extras": {
            "Birthday": null,
            "Age": null,
            "gender": null,
            "Blood Type": null
        },
        "category": "Fictional",
        "subCat1": "Anime",
        "subCat2": "Unlight",
        "createdAt": "Aug 23, 12:21 PM",
        "updatedAt": "155 days"
    },
    {
        "id": "96be09d2-a335-4e31-97d3-64a7feee0145",
        "name": "Marguerite",
        "gender": "f",
        "height": "164.00",
        "extras": {
            "Birthday": null,
            "Age": null,
            "gender": null,
            "Blood Type": null
        },
        "category": "Fictional",
        "subCat1": "Anime",
        "subCat2": "Unlight",
        "createdAt": "Aug 23, 12:21 PM",
        "updatedAt": "155 days"
    },
    {
        "id": "4f73eb2b-02ce-4d86-aeac-dfa70675eb08",
        "name": "Marinella",
        "gender": "f",
        "height": "170.00",
        "extras": {
            "Birthday": null,
            "Age": null,
            "gender": null,
            "Blood Type": null
        },
        "category": "Fictional",
        "subCat1": "Anime",
        "subCat2": "Unlight",
        "createdAt": "Aug 23, 12:21 PM",
        "updatedAt": "155 days"
    },
    {
        "id": "7dab857b-d7d9-4ee8-bc31-96edb7378b62",
        "name": "Marseus",
        "gender": "m",
        "height": "172.00",
        "extras": {
            "Birthday": null,
            "Age": null,
            "gender": null,
            "Blood Type": null
        },
        "category": "Fictional",
        "subCat1": "Anime",
        "subCat2": "Unlight",
        "createdAt": "Aug 23, 12:21 PM",
        "updatedAt": "155 days"
    },
    {
        "id": "32841170-7ec6-46b7-bacf-a1c71b380d09",
        "name": "Mary",
        "gender": "f",
        "height": "139.00",
        "extras": {
            "Birthday": null,
            "Age": null,
            "gender": null,
            "Blood Type": null
        },
        "category": "Fictional",
        "subCat1": "Anime",
        "subCat2": "Unlight",
        "createdAt": "Aug 23, 12:22 PM",
        "updatedAt": "155 days"
    },
    {
        "id": "55881c33-de9e-45f1-8223-158e6de6eb3f",
        "name": "Max",
        "gender": "m",
        "height": "183.00",
        "extras": {
            "Birthday": null,
            "Age": null,
            "gender": null,
            "Blood Type": null
        },
        "category": "Fictional",
        "subCat1": "Anime",
        "subCat2": "Unlight",
        "createdAt": "Aug 23, 12:21 PM",
        "updatedAt": "155 days"
    },
    {
        "id": "c57dacbf-c969-439e-8206-5bcde70ff4bd",
        "name": "Melen",
        "gender": "m",
        "height": "176.00",
        "extras": {
            "Birthday": null,
            "Age": null,
            "gender": null,
            "Blood Type": null
        },
        "category": "Fictional",
        "subCat1": "Anime",
        "subCat2": "Unlight",
        "createdAt": "Aug 23, 12:21 PM",
        "updatedAt": "155 days"
    },
    {
        "id": "c8860426-e8c3-46cb-8c95-fab02bd5fc34",
        "name": "Milian",
        "gender": "m",
        "height": "193.00",
        "extras": {
            "Birthday": null,
            "Age": null,
            "gender": null,
            "Blood Type": null
        },
        "category": "Fictional",
        "subCat1": "Anime",
        "subCat2": "Unlight",
        "createdAt": "Aug 23, 12:21 PM",
        "updatedAt": "155 days"
    },
    {
        "id": "d9a331fe-f20a-4620-8ead-69c3e2062ba4",
        "name": "Mogan",
        "gender": "m",
        "height": "177.00",
        "extras": {
            "Birthday": null,
            "Age": null,
            "gender": null,
            "Blood Type": null
        },
        "category": "Fictional",
        "subCat1": "Anime",
        "subCat2": "Unlight",
        "createdAt": "Aug 23, 12:21 PM",
        "updatedAt": "155 days"
    },
    {
        "id": "76c393fc-2640-48bc-a3a5-0082a214b33f",
        "name": "Nadine",
        "gender": "f",
        "height": "163.00",
        "extras": {
            "Birthday": null,
            "Age": null,
            "gender": null,
            "Blood Type": null
        },
        "category": "Fictional",
        "subCat1": "Anime",
        "subCat2": "Unlight",
        "createdAt": "Aug 23, 12:21 PM",
        "updatedAt": "155 days"
    },
    {
        "id": "7551bd2d-823c-4e1b-b34a-3bd63fd08b7e",
        "name": "Nenem",
        "gender": "f",
        "height": "109.00",
        "extras": {
            "Birthday": null,
            "Age": null,
            "gender": null,
            "Blood Type": null
        },
        "category": "Fictional",
        "subCat1": "Anime",
        "subCat2": "Unlight",
        "createdAt": "Aug 23, 12:22 PM",
        "updatedAt": "155 days"
    },
    {
        "id": "71a5b119-8d22-4d57-a830-64fbbbcadd60",
        "name": "Noichrome",
        "gender": "m",
        "height": "158.00",
        "extras": {
            "Birthday": null,
            "Age": null,
            "gender": null,
            "Blood Type": null
        },
        "category": "Fictional",
        "subCat1": "Anime",
        "subCat2": "Unlight",
        "createdAt": "Aug 23, 12:21 PM",
        "updatedAt": "155 days"
    },
    {
        "id": "ebd737b7-2f72-402d-ab64-eaea6c436c32",
        "name": "Nolla",
        "gender": "m",
        "height": "165.00",
        "extras": {
            "Birthday": null,
            "Age": null,
            "gender": null,
            "Blood Type": null
        },
        "category": "Fictional",
        "subCat1": "Anime",
        "subCat2": "Unlight",
        "createdAt": "Aug 23, 12:22 PM",
        "updatedAt": "155 days"
    },
    {
        "id": "c5924628-41a9-461d-b9f3-2957a504c785",
        "name": "Orang",
        "gender": "m",
        "height": "160.00",
        "extras": {
            "Birthday": null,
            "Age": null,
            "gender": null,
            "Blood Type": null
        },
        "category": "Fictional",
        "subCat1": "Anime",
        "subCat2": "Unlight",
        "createdAt": "Aug 23, 12:21 PM",
        "updatedAt": "155 days"
    },
    {
        "id": "ac766f11-6ad3-4af6-832b-fda88301881c",
        "name": "Palmo",
        "gender": "m",
        "height": "162.00",
        "extras": {
            "Birthday": null,
            "Age": null,
            "gender": null,
            "Blood Type": null
        },
        "category": "Fictional",
        "subCat1": "Anime",
        "subCat2": "Unlight",
        "createdAt": "Aug 23, 12:21 PM",
        "updatedAt": "155 days"
    },
    {
        "id": "b6d04056-c46b-493d-81e4-956a9c77353e",
        "name": "Paulette",
        "gender": "f",
        "height": "145.00",
        "extras": {
            "Birthday": null,
            "Age": null,
            "gender": null,
            "Blood Type": null
        },
        "category": "Fictional",
        "subCat1": "Anime",
        "subCat2": "Unlight",
        "createdAt": "Aug 23, 12:22 PM",
        "updatedAt": "155 days"
    },
    {
        "id": "478f5307-d6ac-47b3-8383-6b444e4290df",
        "name": "Raul",
        "gender": "m",
        "height": "181.00",
        "extras": {
            "Birthday": null,
            "Age": null,
            "gender": null,
            "Blood Type": null
        },
        "category": "Fictional",
        "subCat1": "Anime",
        "subCat2": "Unlight",
        "createdAt": "Aug 23, 12:21 PM",
        "updatedAt": "155 days"
    },
    {
        "id": "d30dfa5e-e262-40ea-932b-3049cb42cdc9",
        "name": "Redgrave",
        "gender": "m",
        "height": "140.00",
        "extras": {
            "Birthday": null,
            "Age": null,
            "gender": null,
            "Blood Type": null
        },
        "category": "Fictional",
        "subCat1": "Anime",
        "subCat2": "Unlight",
        "createdAt": "Aug 23, 12:22 PM",
        "updatedAt": "155 days"
    },
    {
        "id": "130e46e6-f1a9-4081-bd33-038b36e7ea4d",
        "name": "Ricardo",
        "gender": "m",
        "height": "181.00",
        "extras": {
            "Birthday": null,
            "Age": null,
            "gender": null,
            "Blood Type": null
        },
        "category": "Fictional",
        "subCat1": "Anime",
        "subCat2": "Unlight",
        "createdAt": "Aug 23, 12:21 PM",
        "updatedAt": "155 days"
    },
    {
        "id": "f4a067df-462f-4c5f-805f-af841d04ac1e",
        "name": "Riesz",
        "gender": "m",
        "height": "180.00",
        "extras": {
            "Birthday": null,
            "Age": null,
            "gender": null,
            "Blood Type": null
        },
        "category": "Fictional",
        "subCat1": "Anime",
        "subCat2": "Unlight",
        "createdAt": "Aug 23, 12:21 PM",
        "updatedAt": "155 days"
    },
    {
        "id": "e397703b-0c3f-4e25-b79c-75f4cb05e644",
        "name": "Rood",
        "gender": "m",
        "height": "177.00",
        "extras": {
            "Birthday": null,
            "Age": null,
            "gender": null,
            "Blood Type": null
        },
        "category": "Fictional",
        "subCat1": "Anime",
        "subCat2": "Unlight",
        "createdAt": "Aug 23, 12:21 PM",
        "updatedAt": "155 days"
    },
    {
        "id": "aec1c2f0-77f1-46e7-81df-6cbca83b4c52",
        "name": "Rosso",
        "gender": "m",
        "height": "173.00",
        "extras": {
            "Birthday": null,
            "Age": null,
            "gender": null,
            "Blood Type": null
        },
        "category": "Fictional",
        "subCat1": "Anime",
        "subCat2": "Unlight",
        "createdAt": "Aug 23, 12:21 PM",
        "updatedAt": "155 days"
    },
    {
        "id": "ff848064-0759-4172-a05e-b2a1a70a9076",
        "name": "Rudia",
        "gender": "f",
        "height": "153.00",
        "extras": {
            "Birthday": null,
            "Age": null,
            "gender": null,
            "Blood Type": null
        },
        "category": "Fictional",
        "subCat1": "Anime",
        "subCat2": "Unlight",
        "createdAt": "Aug 23, 12:21 PM",
        "updatedAt": "155 days"
    },
    {
        "id": "0910d1e7-c032-4bed-8bce-a66175273b0c",
        "name": "Salgado",
        "gender": "m",
        "height": "178.00",
        "extras": {
            "Birthday": null,
            "Age": null,
            "gender": null,
            "Blood Type": null
        },
        "category": "Fictional",
        "subCat1": "Anime",
        "subCat2": "Unlight",
        "createdAt": "Aug 23, 12:21 PM",
        "updatedAt": "155 days"
    },
    {
        "id": "9cf30783-0aac-49be-b905-bbb7172e2dea",
        "name": "Schillerlee",
        "gender": "m",
        "height": "173.00",
        "extras": {
            "Birthday": null,
            "Age": null,
            "gender": null,
            "Blood Type": null
        },
        "category": "Fictional",
        "subCat1": "Anime",
        "subCat2": "Unlight",
        "createdAt": "Aug 23, 12:21 PM",
        "updatedAt": "155 days"
    },
    {
        "id": "ae3826db-e108-4c75-89fa-a32bf23a5450",
        "name": "Servaas",
        "gender": "m",
        "height": "180.00",
        "extras": {
            "Birthday": null,
            "Age": null,
            "gender": null,
            "Blood Type": null
        },
        "category": "Fictional",
        "subCat1": "Anime",
        "subCat2": "Unlight",
        "createdAt": "Aug 23, 12:21 PM",
        "updatedAt": "155 days"
    },
    {
        "id": "a795037f-d052-49be-b2ba-9a9c849c9ba3",
        "name": "Shalott",
        "gender": "f",
        "height": "159.00",
        "extras": {
            "Birthday": null,
            "Age": null,
            "gender": null,
            "Blood Type": null
        },
        "category": "Fictional",
        "subCat1": "Anime",
        "subCat2": "Unlight",
        "createdAt": "Aug 23, 12:21 PM",
        "updatedAt": "155 days"
    },
    {
        "id": "b536216d-e0d5-46ab-9013-e8940baa8a62",
        "name": "Sheri",
        "gender": "f",
        "height": "155.00",
        "extras": {
            "Birthday": null,
            "Age": null,
            "gender": null,
            "Blood Type": null
        },
        "category": "Fictional",
        "subCat1": "Anime",
        "subCat2": "Unlight",
        "createdAt": "Aug 23, 12:22 PM",
        "updatedAt": "155 days"
    },
    {
        "id": "ad25d29c-388b-4880-a000-2226b07cd62b",
        "name": "Sprout",
        "gender": "m",
        "height": "144.00",
        "extras": {
            "Birthday": null,
            "Age": null,
            "gender": null,
            "Blood Type": null
        },
        "category": "Fictional",
        "subCat1": "Anime",
        "subCat2": "Unlight",
        "createdAt": "Aug 23, 12:22 PM",
        "updatedAt": "155 days"
    },
    {
        "id": "c162e5cf-aee5-4f51-acdf-ecb66a3da2d8",
        "name": "Stacia",
        "gender": "f",
        "height": "157.00",
        "extras": {
            "Birthday": null,
            "Age": null,
            "gender": null,
            "Blood Type": null
        },
        "category": "Fictional",
        "subCat1": "Anime",
        "subCat2": "Unlight",
        "createdAt": "Aug 23, 12:21 PM",
        "updatedAt": "155 days"
    },
    {
        "id": "0d6695fe-3bb9-4265-8f18-2f8c82fa0328",
        "name": "Tyrrell",
        "gender": "m",
        "height": "170.00",
        "extras": {
            "Birthday": null,
            "Age": null,
            "gender": null,
            "Blood Type": null
        },
        "category": "Fictional",
        "subCat1": "Anime",
        "subCat2": "Unlight",
        "createdAt": "Aug 23, 12:21 PM",
        "updatedAt": "155 days"
    },
    {
        "id": "437a9e29-e4c7-4f47-b87a-4797ffe02e81",
        "name": "Veronica",
        "gender": "f",
        "height": "158.00",
        "extras": {
            "Birthday": null,
            "Age": null,
            "gender": null,
            "Blood Type": null
        },
        "category": "Fictional",
        "subCat1": "Anime",
        "subCat2": "Unlight",
        "createdAt": "Aug 23, 12:21 PM",
        "updatedAt": "155 days"
    },
    {
        "id": "152bff86-7ae1-4cb0-a4f6-9063e2529bd0",
        "name": "Voland",
        "gender": "m",
        "height": "144.00",
        "extras": {
            "Birthday": null,
            "Age": null,
            "gender": null,
            "Blood Type": null
        },
        "category": "Fictional",
        "subCat1": "Anime",
        "subCat2": "Unlight",
        "createdAt": "Aug 23, 12:22 PM",
        "updatedAt": "155 days"
    },
    {
        "id": "27026479-5257-4d1d-affe-284e69481819",
        "name": "Walken",
        "gender": "m",
        "height": "177.00",
        "extras": {
            "Birthday": null,
            "Age": null,
            "gender": null,
            "Blood Type": null
        },
        "category": "Fictional",
        "subCat1": "Anime",
        "subCat2": "Unlight",
        "createdAt": "Aug 23, 12:21 PM",
        "updatedAt": "155 days"
    },
    {
        "id": "f42bce5e-fb72-4058-a31f-cbfe6ae45b44",
        "name": "Wilhelm",
        "gender": "m",
        "height": "178.00",
        "extras": {
            "Birthday": null,
            "Age": null,
            "gender": null,
            "Blood Type": null
        },
        "category": "Fictional",
        "subCat1": "Anime",
        "subCat2": "Unlight",
        "createdAt": "Aug 23, 12:21 PM",
        "updatedAt": "155 days"
    }
]